[{"name":"admin","password":"1234","type":1,"id":1,"date":{"createdAt":"Sat Jun 18 2022 15:10:06 GMT+0530 (India Standard Time)"}},{"name":"instructor","password":918149,"type":2,"id":2,"date":{"createdAt":"Sat Jun 18 2022 15:10:28 GMT+0530 (India Standard Time)"}},{"name":"harshana","password":"55555","id":3,"type":3,"date":{"createdAt":"Sat Jun 18 2022 16:18:37 GMT+0530 (India Standard Time)"}},{"name":"walpita","password":"44444","id":4,"type":3,"date":{"createdAt":"Sat Jun 18 2022 16:18:37 GMT+0530 (India Standard Time)"}},{"name":"harshana","password":"55555","id":5,"type":3,"date":{"createdAt":"Sat Jun 18 2022 16:20:51 GMT+0530 (India Standard Time)"}},{"name":"walpita","password":"44444","id":6,"type":3,"date":{"createdAt":"Sat Jun 18 2022 16:20:51 GMT+0530 (India Standard Time)"}}]